accelera/__init__.py
accelera/chunking.py
accelera/config.py
accelera/engine.py
accelera/interceptor.py
accelera/matrix.py
accelera/memory_efficient_engine.py
accelera/memory_manager.py
accelera/subprocess_engine.py
accelera-0.1.2.post2.dist-info/licenses/LICENSE
accelera-0.1.2.post2.dist-info/METADATA
accelera-0.1.2.post2.dist-info/WHEEL
accelera-0.1.2.post2.dist-info/entry_points.txt
accelera-0.1.2.post2.dist-info/top_level.txt
accelera-0.1.2.post2.dist-info/RECORD
